{
 "CCTAAGACAGAACTCT": {
  "mappings": {
   "UMAP": [
    3.97231388092041,
    24.03063201904297
   ]
  },
  "factors": {
   "Leiden Clustering": "Cluster 05",
   "Cell Type Annotation": "plasmablast",
   "Cell Type Annotation Prediction Score": "0.602587822401498"
  }
 },
 "GTTCATTCACTCATAG": {
  "mappings": {
   "UMAP": [
    3.8779447078704834,
    24.08579444885254
   ]
  },
  "factors": {
   "Leiden Clustering": "Cluster 05",
   "Cell Type Annotation": "plasmablast",
   "Cell Type Annotation Prediction Score": "0.7092986019126999"
  }
 },
 "GAGGGATCAATTCACG": {
  "mappings": {
   "UMAP": [
    4.620540618896484,
    23.406461715698242
   ]
  },
  "factors": {
   "Leiden Clustering": "Cluster 05",
   "Cell Type Annotation": "B cell",
   "Cell Type Annotation Prediction Score": "0.7908523032899499"
  }
 },
 "AACAGGGCATGACTTG": {
  "mappings": {
   "UMAP": [
    7.996124267578125,
    3.6404261589050293
   ]
  },
  "factors": {
   "Leiden Clustering": "Cluster 07",
   "Cell Type Annotation": "hematopoietic stem cell",
   "Cell Type Annotation Prediction Score": "0.7309207332200821"
  }
 },
 "CCTCCAAGTGCCCGTA": {
  "mappings": {
   "UMAP": [
    4.219403266906738,
    24.04006004333496
   ]
  },
  "factors": {
   "Leiden Clustering": "Cluster 05",
   "Cell Type Annotation": "plasmablast",
   "Cell Type Annotation Prediction Score": "0.7114575684600641"
  }
 },
 "CCATCACGTACCTATG": {
  "mappings": {
   "UMAP": [
    6.462860584259033,
    22.275108337402344
   ]
  },
  "factors": {
   "Leiden Clustering": "Cluster 05",
   "Cell Type Annotation": "B cell",
   "Cell Type Annotation Prediction Score": "1.0"
  }
 },
 "GCGATCGGTGATTGGG": {
  "mappings": {
   "UMAP": [
    8.07612133026123,
    3.1962718963623047
   ]
  },
  "factors": {
   "Leiden Clustering": "Cluster 07",
   "Cell Type Annotation": "hematopoietic stem cell",
   "Cell Type Annotation Prediction Score": "0.943308401723698"
  }
 },
 "AGTACCAGTAGTAAGT": {
  "mappings": {
   "UMAP": [
    3.848541021347046,
    24.173274993896484
   ]
  },
  "factors": {
   "Leiden Clustering": "Cluster 05",
   "Cell Type Annotation": "plasmablast",
   "Cell Type Annotation Prediction Score": "0.751685257508346"
  }
 },
 "TCTACATCACAGAGAC": {
  "mappings": {
   "UMAP": [
    4.061056613922119,
    23.832805633544922
   ]
  },
  "factors": {
   "Leiden Clustering": "Cluster 05",
   "Cell Type Annotation": "plasmablast",
   "Cell Type Annotation Prediction Score": "0.700644881185326"
  }
 },
 "CCACTTGGTACTCCGG": {
  "mappings": {
   "UMAP": [
    11.391741752624512,
    12.45070743560791
   ]
  },
  "factors": {
   "Leiden Clustering": "Cluster 09",
   "Cell Type Annotation": "plasma cell",
   "Cell Type Annotation Prediction Score": "1.0"
  }
 },
 "ACTTTGTTCTTTGCAT": {
  "mappings": {
   "UMAP": [
    8.204302787780762,
    3.326850414276123
   ]
  },
  "factors": {
   "Leiden Clustering": "Cluster 07",
   "Cell Type Annotation": "hematopoietic stem cell",
   "Cell Type Annotation Prediction Score": "0.939858407541739"
  }
 },
 "CATGCTCTCGAGAAGC": {
  "mappings": {
   "UMAP": [
    11.242717742919922,
    11.928844451904297
   ]
  },
  "factors": {
   "Leiden Clustering": "Cluster 09",
   "Cell Type Annotation": "plasma cell",
   "Cell Type Annotation Prediction Score": "1.0"
  }
 },
 "TCTACATTCCCAAGCG": {
  "mappings": {
   "UMAP": [
    10.844888687133789,
    12.558363914489746
   ]
  },
  "factors": {
   "Leiden Clustering": "Cluster 09",
   "Cell Type Annotation": "plasma cell",
   "Cell Type Annotation Prediction Score": "1.0"
  }
 },
 "TGGAGGACACGCGTGT": {
  "mappings": {
   "UMAP": [
    6.350910186767578,
    3.744248390197754
   ]
  },
  "factors": {
   "Leiden Clustering": "Cluster 08",
   "Cell Type Annotation": "hematopoietic stem cell",
   "Cell Type Annotation Prediction Score": "0.330550439372868"
  }
 },
 "TTGCATTCAATGTTGC": {
  "mappings": {
   "UMAP": [
    5.998854637145996,
    23.48809242248535
   ]
  },
  "factors": {
   "Leiden Clustering": "Cluster 05",
   "Cell Type Annotation": "B cell",
   "Cell Type Annotation Prediction Score": "1.0"
  }
 },
 "AGCCAGCTCCACCTCA": {
  "mappings": {
   "UMAP": [
    3.650548219680786,
    23.85667610168457
   ]
  },
  "factors": {
   "Leiden Clustering": "Cluster 05",
   "Cell Type Annotation": "plasmablast",
   "Cell Type Annotation Prediction Score": "0.44273656191849897"
  }
 },
 "AAGCAGTGGTATCAAC": {
  "mappings": {
   "UMAP": [
    3.330662965774536,
    21.95383071899414
   ]
  },
  "factors": {
   "Leiden Clustering": "Cluster 05",
   "Cell Type Annotation": "B cell",
   "Cell Type Annotation Prediction Score": "0.589099533194315"
  }
 },
 "CTCAGTCTCGATTTCT": {
  "mappings": {
   "UMAP": [
    3.65726375579834,
    24.01825523376465
   ]
  },
  "factors": {
   "Leiden Clustering": "Cluster 05",
   "Cell Type Annotation": "hematopoietic stem cell",
   "Cell Type Annotation Prediction Score": "0.536018395648272"
  }
 },
 "ACGCACGGTGTTTACG": {
  "mappings": {
   "UMAP": [
    7.1116180419921875,
    4.05258321762085
   ]
  },
  "factors": {
   "Leiden Clustering": "Cluster 08",
   "Cell Type Annotation": "CD141-positive myeloid dendritic cell",
   "Cell Type Annotation Prediction Score": "0.841034599582662"
  }
 },
 "CATCGGGAGTCCCAGC": {
  "mappings": {
   "UMAP": [
    10.74029541015625,
    11.979586601257324
   ]
  },
  "factors": {
   "Leiden Clustering": "Cluster 09",
   "Cell Type Annotation": "plasma cell",
   "Cell Type Annotation Prediction Score": "1.0"
  }
 },
 "AAAGAACAGCTACAAA": {
  "mappings": {
   "UMAP": [
    5.992628574371338,
    3.902203321456909
   ]
  },
  "factors": {
   "Leiden Clustering": "Cluster 08",
   "Cell Type Annotation": "CD14-positive monocyte",
   "Cell Type Annotation Prediction Score": "0.503802173799851"
  }
 },
 "TTCTTGATCTAACACG": {
  "mappings": {
   "UMAP": [
    5.958173751831055,
    21.145532608032227
   ]
  },
  "factors": {
   "Leiden Clustering": "Cluster 05",
   "Cell Type Annotation": "B cell",
   "Cell Type Annotation Prediction Score": "1.0"
  }
 },
 "AGGGAGTCAGCCCACA": {
  "mappings": {
   "UMAP": [
    3.6161842346191406,
    23.44786834716797
   ]
  },
  "factors": {
   "Leiden Clustering": "Cluster 05",
   "Cell Type Annotation": "B cell",
   "Cell Type Annotation Prediction Score": "0.501192121675334"
  }
 },
 "ATGGTTGTCACTGGGC": {
  "mappings": {
   "UMAP": [
    11.548601150512695,
    12.21356201171875
   ]
  },
  "factors": {
   "Leiden Clustering": "Cluster 09",
   "Cell Type Annotation": "plasma cell",
   "Cell Type Annotation Prediction Score": "1.0"
  }
 },
 "AACTTCTGTCTACGAT": {
  "mappings": {
   "UMAP": [
    10.527569770812988,
    11.828376770019531
   ]
  },
  "factors": {
   "Leiden Clustering": "Cluster 09",
   "Cell Type Annotation": "plasma cell",
   "Cell Type Annotation Prediction Score": "0.997361990442739"
  }
 }
}